physh/__init__.py
physh-0.1.2.dist-info/LICENSE.MD
physh-0.1.2.dist-info/METADATA
physh-0.1.2.dist-info/WHEEL
physh-0.1.2.dist-info/top_level.txt
physh-0.1.2.dist-info/RECORD
