Metadata-Version: 2.1
Name: physh
Version: 0.1.2
Summary: run shell commands with this thin wrapper around the subprocess module
Home-page: https://github.com/CoinBR/physh/tree/master
Author: Pedro 'Coin' Duarte
Author-email: coinbr@gmail.com
License: UNKNOWN
Platform: UNKNOWN
Classifier: Programming Language :: Python :: 3.6
Classifier: License :: CC0 1.0 Universal (CC0 1.0) Public Domain Dedication
Classifier: Operating System :: POSIX :: Linux
